git_cherry_pick_helper/__init__.py
git_cherry_pick_helper-0.1.1.dist-info/METADATA
git_cherry_pick_helper-0.1.1.dist-info/WHEEL
git_cherry_pick_helper-0.1.1.dist-info/entry_points.txt
git_cherry_pick_helper-0.1.1.dist-info/top_level.txt
git_cherry_pick_helper-0.1.1.dist-info/RECORD
