Metadata-Version: 2.1
Name: git-cherry-pick-helper
Version: 0.1.1
Summary: Simplify cherry-picking for messy git workflows
Home-page: https://github.com/dschwoerer/git-cherry-pick-helper
Author: David Bold
Author-email: davidsch@fedoraproject.org
License: GPL
Project-URL: Tracker, https://github.com/dschwoerer/git-cherry-pick-helper/issues
Classifier: Development Status :: 4 - Beta
Classifier: Intended Audience :: Science/Research
Classifier: Intended Audience :: Education
Classifier: Intended Audience :: Developers
Classifier: License :: OSI Approved :: GNU General Public License v3 or later (GPLv3+)
Classifier: Natural Language :: English
Classifier: Operating System :: POSIX :: Linux
Classifier: Programming Language :: Python :: 3.7
Classifier: Programming Language :: Python :: 3.8
Classifier: Programming Language :: Python :: 3.9
Classifier: Programming Language :: Python :: 3.10
Classifier: Programming Language :: Python :: 3.11
Classifier: Topic :: Scientific/Engineering :: Visualization
Requires-Dist: numpy
Requires-Dist: GitPython
